proxyarrays/__init__.py
proxyarrays/dataclasses/__init__.py
proxyarrays/directorytimeseries/__init__.py
proxyarrays/directorytimeseries/basedirectorytimeseries.py
proxyarrays/directorytimeseries/directorytimeseriesproxy.py
proxyarrays/filetimeseries/__init__.py
proxyarrays/filetimeseries/basecontainerfiletimeseries.py
proxyarrays/header.py
proxyarrays/proxyarray/__init__.py
proxyarrays/proxyarray/baseproxyarray.py
proxyarrays/proxyarray/blankproxyarray.py
proxyarrays/proxyarray/containerproxyarray.py
proxyarrays/proxyarray/proxyarray.py
proxyarrays/py.typed
proxyarrays/timeaxis/__init__.py
proxyarrays/timeaxis/basetimeaxis.py
proxyarrays/timeaxis/blanktimeaxis.py
proxyarrays/timeaxis/containertimeaxis.py
proxyarrays/timeaxis/timeaxisproxy.py
proxyarrays/timeproxy/__init__.py
proxyarrays/timeproxy/basetimeproxy.py
proxyarrays/timeproxy/blanktimeproxy.py
proxyarrays/timeproxy/timeproxy.py
proxyarrays/timeseries/__init__.py
proxyarrays/timeseries/basetimeseries.py
proxyarrays/timeseries/blanktimeseries.py
proxyarrays/timeseries/containertimeseries.py
proxyarrays/timeseries/timeseriesproxy.py
proxyarrays-0.6.0.dist-info/LICENSE.rst
proxyarrays-0.6.0.dist-info/METADATA
proxyarrays-0.6.0.dist-info/WHEEL
proxyarrays-0.6.0.dist-info/entry_points.txt
proxyarrays-0.6.0.dist-info/RECORD
