Metadata-Version: 2.1
Name: proxyarrays
Version: 0.6.0
Summary: Numpy array like objects that are proxies for remote or virtual arrays.
Home-page: https://github.com/FongAnthonyM/python-proxyarrays
License: MIT
Author: Anthony Fong
Author-email: FongAnthonyM@gmail.com
Requires-Python: >=3.10,<4.0
Classifier: Development Status :: 3 - Alpha
Classifier: License :: OSI Approved :: MIT License
Classifier: Programming Language :: Python :: 3
Classifier: Programming Language :: Python :: 3.10
Classifier: Programming Language :: Python :: 3.11
Requires-Dist: baseobjects (>=1.11.0)
Requires-Dist: dspobjects (>=0.4.0)
Requires-Dist: numpy (>=1.25.1)
Requires-Dist: scipy (>=1.6.1)
Project-URL: Changelog, https://github.com/FongAnthonyM/python-proxyarrays/releases
Project-URL: Documentation, https://python-proxyarrays.readthedocs.io
Project-URL: Repository, https://github.com/FongAnthonyM/python-proxyarrays
